testfarm_agents_utils.py
testfarm_benchmarks_utils.py
testfarm_unit_tests_utils.py
testfarmutils-0.2.2.dist-info/licenses/LICENSE
testfarmutils-0.2.2.dist-info/METADATA
testfarmutils-0.2.2.dist-info/WHEEL
testfarmutils-0.2.2.dist-info/top_level.txt
testfarmutils-0.2.2.dist-info/RECORD
