Metadata-Version: 2.4
Name: testfarmutils
Version: 0.2.2
Summary: TestFarm utilities for tests creation and execution.
Author-email: Grzegorz Powała <gpowala@gmail.com>
License-File: LICENSE
Dynamic: license-file
